auto_self_params/__init__.py
auto_self_params/auto_self_params.py
auto_self_params-0.0.2.dist-info/LICENSE
auto_self_params-0.0.2.dist-info/METADATA
auto_self_params-0.0.2.dist-info/WHEEL
auto_self_params-0.0.2.dist-info/top_level.txt
auto_self_params-0.0.2.dist-info/RECORD
