Metadata-Version: 2.1
Name: auto-self-params
Version: 0.0.2
Summary: Automatic creation of self properties from parameters.
Home-page: https://github.com/GadgetSteve/auto_self_params
Author: Steve Barmes
Author-email: gadgetsteve@hotmail.com
License: MIT License
Platform: UNKNOWN
Classifier: Programming Language :: Python :: 3
Classifier: License :: OSI Approved :: MIT License
Classifier: Operating System :: OS Independent
Classifier: Intended Audience :: Developers
Requires-Python: >=3.6
